pyharmonic_native-0.1.0.dist-info/METADATA
pyharmonic_native-0.1.0.dist-info/WHEEL
pyharmonic_native/__init__.py
pyharmonic_native/ffi.py
pyharmonic_native/libpyharmonic_native.dylib
pyharmonic_native-0.1.0.dist-info/RECORD
