Metadata-Version: 2.4
Name: pyharmonic_native
Version: 0.1.0
Summary: 谐波减速器项目的本地扩展模块（占位）
